WH_Utils/__init__.py
WH_Utils/__version__.py
WH_Utils/Analytics/__init__.py
WH_Utils/Analytics/Events/Base.py
WH_Utils/Analytics/Events/__init__.py
WH_Utils/Analytics/Prospects/API.py
WH_Utils/Analytics/Prospects/Hawkrank.py
WH_Utils/Analytics/Prospects/Nodes.py
WH_Utils/Analytics/Prospects/__init__.py
WH_Utils/Automation/__init__.py
WH_Utils/Automation/ParseRegForms/ParseRegD.py
WH_Utils/Automation/ParseRegForms/Utils.py
WH_Utils/Automation/ParseRegForms/__init__.py
WH_Utils/Connectors/__init__.py
WH_Utils/Connectors/Coresignal/__init__.py
WH_Utils/Connectors/Coresignal/functions.py
WH_Utils/Connectors/SEC/__init__.py
WH_Utils/Connectors/SEC/functions.py
WH_Utils/Connectors/WH/__init__.py
WH_Utils/Connectors/WH/api.py
WH_Utils/Connectors/WH/ingress.py
WH_Utils/External/__init__.py
WH_Utils/External/Coresignal/__init__.py
WH_Utils/External/Coresignal/functions.py
WH_Utils/External/Typeform/__init__.py
WH_Utils/Objects/Company.py
WH_Utils/Objects/Enums.py
WH_Utils/Objects/Event.py
WH_Utils/Objects/Object_utils.py
WH_Utils/Objects/Prospect.py
WH_Utils/Objects/User.py
WH_Utils/Objects/__init__.py
WH_Utils/Objects/__main__.py
WH_Utils/Utils/__init__.py
WH_Utils/Utils/global_utils.py
WH_Utils/Utils/test_utils.py
tests/__init__.py
tests/test_objects/__init__.py
tests/test_objects/test_company.py
tests/test_objects/test_event.py
tests/test_objects/test_prospect.py
tests/test_objects/test_user.py
WH_Utils-0.0.1.dist-info/LICENSE
WH_Utils-0.0.1.dist-info/METADATA
WH_Utils-0.0.1.dist-info/WHEEL
WH_Utils-0.0.1.dist-info/top_level.txt
WH_Utils-0.0.1.dist-info/RECORD
