Metadata-Version: 2.1
Name: WH-Utils
Version: 0.0.1
Summary: py-package-template - Package Template Project Generator
Home-page: 
Author: McClain Thiel
Author-email: mcclain@wealthawk.com
License: Apache 2.0
Keywords: package development template
Classifier: Development Status :: 4 - Beta
Classifier: Intended Audience :: Developers
Classifier: Programming Language :: Python :: 3.8
Requires-Python: >=3.7.*
License-File: LICENSE
Requires-Dist: numpy
Requires-Dist: requests
Requires-Dist: pandas
Requires-Dist: validators
Requires-Dist: pydantic
